LICENSE.txt
MANIFEST.in
README.md
requirements-dev.txt
requirements.txt
setup.py
django_cassandra_db.egg-info/PKG-INFO
django_cassandra_db.egg-info/SOURCES.txt
django_cassandra_db.egg-info/dependency_links.txt
django_cassandra_db.egg-info/not-zip-safe
django_cassandra_db.egg-info/requires.txt
django_cassandra_db.egg-info/top_level.txt
django_cassandra_engine/__init__.py
django_cassandra_engine/apps.py
django_cassandra_engine/compat.py
django_cassandra_engine/connection.py
django_cassandra_engine/test.py
django_cassandra_engine/utils.py
django_cassandra_engine/base/__init__.py
django_cassandra_engine/base/client.py
django_cassandra_engine/base/creation.py
django_cassandra_engine/base/features.py
django_cassandra_engine/base/introspection.py
django_cassandra_engine/base/operations.py
django_cassandra_engine/base/schema.py
django_cassandra_engine/base/validation.py
django_cassandra_engine/management/__init__.py
django_cassandra_engine/management/commands/__init__.py
django_cassandra_engine/management/commands/flush.py
django_cassandra_engine/management/commands/makemigrations.py
django_cassandra_engine/management/commands/migrate.py
django_cassandra_engine/management/commands/sync_cassandra.py
django_cassandra_engine/management/commands/syncdb.py
django_cassandra_engine/models/__init__.py
django_cassandra_engine/models/constants.py
django_cassandra_engine/models/django_field_methods.py
django_cassandra_engine/models/django_model_methods.py
django_cassandra_engine/models/fields.py
django_cassandra_engine/rest/__init__.py
django_cassandra_engine/rest/serializers.py
django_cassandra_engine/sessions/__init__.py
django_cassandra_engine/sessions/models.py
django_cassandra_engine/sessions/backends/__init__.py
django_cassandra_engine/sessions/backends/cached_db.py
django_cassandra_engine/sessions/backends/db.py