Metadata-Version: 2.1
Name: django-cassandra-db
Version: 0.0.2
Summary: Django Cassandra DB
Home-page: http://github.com/Ariwonto/django-cassandra-engine
Author: Ariwonto
Author-email: info@ariwonto.com
License: 2-clause BSD
Download-URL: https://github.com/Ariwonto/django-cassandra-engine/tarball/master
Keywords: django cassandra engine backend driver wrapper database nonrel cqlengine
Platform: UNKNOWN
Classifier: Development Status :: 5 - Production/Stable
Classifier: Environment :: Web Environment
Classifier: Environment :: Plugins
Classifier: Framework :: Django
Classifier: Intended Audience :: Developers
Classifier: License :: OSI Approved :: BSD License
Classifier: Operating System :: OS Independent
Classifier: Programming Language :: Python
Classifier: Programming Language :: Python :: 3.6
Classifier: Programming Language :: Python :: 3.7
Classifier: Programming Language :: Python :: 3.8
Classifier: Topic :: Database
Classifier: Topic :: Internet
Classifier: Topic :: Software Development :: Libraries :: Python Modules
